<?xml version="1.0" encoding="UTF-8" ?>
<!DOCTYPE generatorConfiguration PUBLIC "-//mybatis.org//DTD MyBatis Generator Configuration 1.0//EN" "http://mybatis.org/dtd/mybatis-generator-config_1_0.dtd" >
<generatorConfiguration>
  <context id="context1" targetRuntime="MyBatis3">
    <jdbcConnection connectionURL="jdbc:postgresql://localhost:5432/fois_smile" driverClass="org.postgresql.Driver" password="root" userId="postgres" />
    <javaModelGenerator targetPackage="com.fois.Back_end_fois_smile.entity" targetProject="Back_end_fois_smile" />
    <sqlMapGenerator targetPackage="com.fois.Back_end_fois_smile.mapper" targetProject="Back_end_fois_smile" />
    <javaClientGenerator targetPackage="com.fois.Back_end_fois_smile.mapper" targetProject="Back_end_fois_smile" type="XMLMAPPER">
    </javaClientGenerator>
    <table schema="schema01" tableName="%" >
      </table>
  </context>
</generatorConfiguration>